CODE_OF_CONDUCT.md
LICENSE
MANIFEST.in
README.md
setup.cfg
setup.py
versioneer.py
pyelementary/__init__.py
pyelementary/_version.py
pyelementary/exceptions.py
pyelementary/pyelementary.py
pyelementary.egg-info/PKG-INFO
pyelementary.egg-info/SOURCES.txt
pyelementary.egg-info/dependency_links.txt
pyelementary.egg-info/top_level.txt
pyelementary/data/README.md
pyelementary/data/elements.json
pyelementary/data/test.py
pyelementary/tests/__init__.py
pyelementary/tests/base.py
pyelementary/tests/datafiles.py
pyelementary/tests/test_openff.py
pyelementary/tests/test_openmm.py
pyelementary/tests/test_pydantic.py
pyelementary/tests/test_pyelementary.py
pyelementary/tests/test_unyt.py
pyelementary/tests/.hypothesis/examples/26593b5ab9cf12d3/cd6bd1dcfebeffe9
pyelementary/tests/.hypothesis/examples/463a13a8bfbb8845/bec021b4f368e306
pyelementary/tests/.hypothesis/examples/599646ba981169ff/cd6bd1dcfebeffe9
pyelementary/tests/.hypothesis/examples/91ea57ab6daec205/cd6bd1dcfebeffe9
pyelementary/tests/.hypothesis/examples/b8ea2a719d1a1950/bec021b4f368e306
pyelementary/tests/.hypothesis/examples/de92f1c22b3b4810/cd6bd1dcfebeffe9
pyelementary/tests/.hypothesis/unicode_data/13.0.0/charmap.json.gz
pyelementary/tests/data/vegetal.json