Metadata-Version: 2.1
Name: pyelementary
Version: 0.1.2
Summary:  Yet another elements package
Home-page: UNKNOWN
Author: Lily Wang
Author-email: lily@minium.com.au
License: MIT
Platform: UNKNOWN
License-File: LICENSE
